<?xml version="1.0" encoding="UTF-8"?>
<!DOCTYPE mapper PUBLIC "-//mybatis.org//DTD Mapper 3.0//EN" "http://mybatis.org/dtd/mybatis-3-mapper.dtd">
<mapper namespace="skyline.stp.repository.dao.StpScheduleLogMapper">
  <resultMap id="BaseResultMap" type="skyline.stp.repository.model.StpScheduleLog">
    <!--
      WARNING - @mbggenerated
      This element is automatically generated by MyBatis Generator, do not modify.
      This element was generated on Mon Aug 31 14:23:26 CST 2015.
    -->
    <result column="PKID" jdbcType="VARCHAR" property="pkid" />
    <result column="TABLENAME" jdbcType="VARCHAR" property="tablename" />
    <result column="TYPE" jdbcType="VARCHAR" property="type" />
    <result column="ROWPKID" jdbcType="VARCHAR" property="rowpkid" />
    <result column="JOBCODE" jdbcType="VARCHAR" property="jobcode" />
    <result column="JOBNAME" jdbcType="VARCHAR" property="jobname" />
    <result column="JOBGROUP" jdbcType="VARCHAR" property="jobgroup" />
    <result column="JOBDESC" jdbcType="VARCHAR" property="jobdesc" />
    <result column="JOBTIME" jdbcType="VARCHAR" property="jobtime" />
    <result column="JOBUSERID" jdbcType="VARCHAR" property="jobuserid" />
    <result column="JOBUSERNAME" jdbcType="VARCHAR" property="jobusername" />
    <result column="REMARK" jdbcType="VARCHAR" property="remark" />
  </resultMap>
  <sql id="Example_Where_Clause">
    <!--
      WARNING - @mbggenerated
      This element is automatically generated by MyBatis Generator, do not modify.
      This element was generated on Mon Aug 31 14:23:26 CST 2015.
    -->
    <where>
      <foreach collection="oredCriteria" item="criteria" separator="or">
        <if test="criteria.valid">
          <trim prefix="(" prefixOverrides="and" suffix=")">
            <foreach collection="criteria.criteria" item="criterion">
              <choose>
                <when test="criterion.noValue">
                  and ${criterion.condition}
                </when>
                <when test="criterion.singleValue">
                  and ${criterion.condition} #{criterion.value}
                </when>
                <when test="criterion.betweenValue">
                  and ${criterion.condition} #{criterion.value} and #{criterion.secondValue}
                </when>
                <when test="criterion.listValue">
                  and ${criterion.condition}
                  <foreach close=")" collection="criterion.value" item="listItem" open="(" separator=",">
                    #{listItem}
                  </foreach>
                </when>
              </choose>
            </foreach>
          </trim>
        </if>
      </foreach>
    </where>
  </sql>
  <sql id="Update_By_Example_Where_Clause">
    <!--
      WARNING - @mbggenerated
      This element is automatically generated by MyBatis Generator, do not modify.
      This element was generated on Mon Aug 31 14:23:26 CST 2015.
    -->
    <where>
      <foreach collection="example.oredCriteria" item="criteria" separator="or">
        <if test="criteria.valid">
          <trim prefix="(" prefixOverrides="and" suffix=")">
            <foreach collection="criteria.criteria" item="criterion">
              <choose>
                <when test="criterion.noValue">
                  and ${criterion.condition}
                </when>
                <when test="criterion.singleValue">
                  and ${criterion.condition} #{criterion.value}
                </when>
                <when test="criterion.betweenValue">
                  and ${criterion.condition} #{criterion.value} and #{criterion.secondValue}
                </when>
                <when test="criterion.listValue">
                  and ${criterion.condition}
                  <foreach close=")" collection="criterion.value" item="listItem" open="(" separator=",">
                    #{listItem}
                  </foreach>
                </when>
              </choose>
            </foreach>
          </trim>
        </if>
      </foreach>
    </where>
  </sql>
  <sql id="Base_Column_List">
    <!--
      WARNING - @mbggenerated
      This element is automatically generated by MyBatis Generator, do not modify.
      This element was generated on Mon Aug 31 14:23:26 CST 2015.
    -->
    PKID, TABLENAME, TYPE, ROWPKID, JOBCODE, JOBNAME, JOBGROUP, JOBDESC, JOBTIME, JOBUSERID, 
    JOBUSERNAME, REMARK
  </sql>
  <select id="selectByExample" parameterType="skyline.stp.repository.model.StpScheduleLogExample" resultMap="BaseResultMap">
    <!--
      WARNING - @mbggenerated
      This element is automatically generated by MyBatis Generator, do not modify.
      This element was generated on Mon Aug 31 14:23:26 CST 2015.
    -->
    select
    <if test="distinct">
      distinct
    </if>
    <include refid="Base_Column_List" />
    from STP_SCHEDULE_LOG
    <if test="_parameter != null">
      <include refid="Example_Where_Clause" />
    </if>
    <if test="orderByClause != null">
      order by ${orderByClause}
    </if>
  </select>
  <delete id="deleteByExample" parameterType="skyline.stp.repository.model.StpScheduleLogExample">
    <!--
      WARNING - @mbggenerated
      This element is automatically generated by MyBatis Generator, do not modify.
      This element was generated on Mon Aug 31 14:23:26 CST 2015.
    -->
    delete from STP_SCHEDULE_LOG
    <if test="_parameter != null">
      <include refid="Example_Where_Clause" />
    </if>
  </delete>
  <insert id="insert" parameterType="skyline.stp.repository.model.StpScheduleLog">
    <!--
      WARNING - @mbggenerated
      This element is automatically generated by MyBatis Generator, do not modify.
      This element was generated on Mon Aug 31 14:23:26 CST 2015.
    -->
    <selectKey keyProperty="pkid" order="BEFORE" resultType="java.lang.String">
      select sys_guid() from dual
    </selectKey>
    insert into STP_SCHEDULE_LOG (PKID, TABLENAME, TYPE, 
      ROWPKID, JOBCODE, JOBNAME, 
      JOBGROUP, JOBDESC, JOBTIME, 
      JOBUSERID, JOBUSERNAME, REMARK
      )
    values (#{pkid,jdbcType=VARCHAR}, #{tablename,jdbcType=VARCHAR}, #{type,jdbcType=VARCHAR}, 
      #{rowpkid,jdbcType=VARCHAR}, #{jobcode,jdbcType=VARCHAR}, #{jobname,jdbcType=VARCHAR}, 
      #{jobgroup,jdbcType=VARCHAR}, #{jobdesc,jdbcType=VARCHAR}, #{jobtime,jdbcType=VARCHAR}, 
      #{jobuserid,jdbcType=VARCHAR}, #{jobusername,jdbcType=VARCHAR}, #{remark,jdbcType=VARCHAR}
      )
  </insert>
  <insert id="insertSelective" parameterType="skyline.stp.repository.model.StpScheduleLog">
    <!--
      WARNING - @mbggenerated
      This element is automatically generated by MyBatis Generator, do not modify.
      This element was generated on Mon Aug 31 14:23:26 CST 2015.
    -->
    <selectKey keyProperty="pkid" order="BEFORE" resultType="java.lang.String">
      select sys_guid() from dual
    </selectKey>
    insert into STP_SCHEDULE_LOG
    <trim prefix="(" suffix=")" suffixOverrides=",">
      PKID,
      <if test="tablename != null">
        TABLENAME,
      </if>
      <if test="type != null">
        TYPE,
      </if>
      <if test="rowpkid != null">
        ROWPKID,
      </if>
      <if test="jobcode != null">
        JOBCODE,
      </if>
      <if test="jobname != null">
        JOBNAME,
      </if>
      <if test="jobgroup != null">
        JOBGROUP,
      </if>
      <if test="jobdesc != null">
        JOBDESC,
      </if>
      <if test="jobtime != null">
        JOBTIME,
      </if>
      <if test="jobuserid != null">
        JOBUSERID,
      </if>
      <if test="jobusername != null">
        JOBUSERNAME,
      </if>
      <if test="remark != null">
        REMARK,
      </if>
    </trim>
    <trim prefix="values (" suffix=")" suffixOverrides=",">
      #{pkid,jdbcType=VARCHAR},
      <if test="tablename != null">
        #{tablename,jdbcType=VARCHAR},
      </if>
      <if test="type != null">
        #{type,jdbcType=VARCHAR},
      </if>
      <if test="rowpkid != null">
        #{rowpkid,jdbcType=VARCHAR},
      </if>
      <if test="jobcode != null">
        #{jobcode,jdbcType=VARCHAR},
      </if>
      <if test="jobname != null">
        #{jobname,jdbcType=VARCHAR},
      </if>
      <if test="jobgroup != null">
        #{jobgroup,jdbcType=VARCHAR},
      </if>
      <if test="jobdesc != null">
        #{jobdesc,jdbcType=VARCHAR},
      </if>
      <if test="jobtime != null">
        #{jobtime,jdbcType=VARCHAR},
      </if>
      <if test="jobuserid != null">
        #{jobuserid,jdbcType=VARCHAR},
      </if>
      <if test="jobusername != null">
        #{jobusername,jdbcType=VARCHAR},
      </if>
      <if test="remark != null">
        #{remark,jdbcType=VARCHAR},
      </if>
    </trim>
  </insert>
  <select id="countByExample" parameterType="skyline.stp.repository.model.StpScheduleLogExample" resultType="java.lang.Integer">
    <!--
      WARNING - @mbggenerated
      This element is automatically generated by MyBatis Generator, do not modify.
      This element was generated on Mon Aug 31 14:23:26 CST 2015.
    -->
    select count(*) from STP_SCHEDULE_LOG
    <if test="_parameter != null">
      <include refid="Example_Where_Clause" />
    </if>
  </select>
  <update id="updateByExampleSelective" parameterType="map">
    <!--
      WARNING - @mbggenerated
      This element is automatically generated by MyBatis Generator, do not modify.
      This element was generated on Mon Aug 31 14:23:26 CST 2015.
    -->
    update STP_SCHEDULE_LOG
    <set>
      <if test="record.pkid != null">
        PKID = #{record.pkid,jdbcType=VARCHAR},
      </if>
      <if test="record.tablename != null">
        TABLENAME = #{record.tablename,jdbcType=VARCHAR},
      </if>
      <if test="record.type != null">
        TYPE = #{record.type,jdbcType=VARCHAR},
      </if>
      <if test="record.rowpkid != null">
        ROWPKID = #{record.rowpkid,jdbcType=VARCHAR},
      </if>
      <if test="record.jobcode != null">
        JOBCODE = #{record.jobcode,jdbcType=VARCHAR},
      </if>
      <if test="record.jobname != null">
        JOBNAME = #{record.jobname,jdbcType=VARCHAR},
      </if>
      <if test="record.jobgroup != null">
        JOBGROUP = #{record.jobgroup,jdbcType=VARCHAR},
      </if>
      <if test="record.jobdesc != null">
        JOBDESC = #{record.jobdesc,jdbcType=VARCHAR},
      </if>
      <if test="record.jobtime != null">
        JOBTIME = #{record.jobtime,jdbcType=VARCHAR},
      </if>
      <if test="record.jobuserid != null">
        JOBUSERID = #{record.jobuserid,jdbcType=VARCHAR},
      </if>
      <if test="record.jobusername != null">
        JOBUSERNAME = #{record.jobusername,jdbcType=VARCHAR},
      </if>
      <if test="record.remark != null">
        REMARK = #{record.remark,jdbcType=VARCHAR},
      </if>
    </set>
    <if test="_parameter != null">
      <include refid="Update_By_Example_Where_Clause" />
    </if>
  </update>
  <update id="updateByExample" parameterType="map">
    <!--
      WARNING - @mbggenerated
      This element is automatically generated by MyBatis Generator, do not modify.
      This element was generated on Mon Aug 31 14:23:26 CST 2015.
    -->
    update STP_SCHEDULE_LOG
    set PKID = #{record.pkid,jdbcType=VARCHAR},
      TABLENAME = #{record.tablename,jdbcType=VARCHAR},
      TYPE = #{record.type,jdbcType=VARCHAR},
      ROWPKID = #{record.rowpkid,jdbcType=VARCHAR},
      JOBCODE = #{record.jobcode,jdbcType=VARCHAR},
      JOBNAME = #{record.jobname,jdbcType=VARCHAR},
      JOBGROUP = #{record.jobgroup,jdbcType=VARCHAR},
      JOBDESC = #{record.jobdesc,jdbcType=VARCHAR},
      JOBTIME = #{record.jobtime,jdbcType=VARCHAR},
      JOBUSERID = #{record.jobuserid,jdbcType=VARCHAR},
      JOBUSERNAME = #{record.jobusername,jdbcType=VARCHAR},
      REMARK = #{record.remark,jdbcType=VARCHAR}
    <if test="_parameter != null">
      <include refid="Update_By_Example_Where_Clause" />
    </if>
  </update>
</mapper>